exa_logging/__init__.py
exa_logging/config/__init__.py
exa_logging-0.1.0.dist-info/METADATA
exa_logging-0.1.0.dist-info/WHEEL
exa_logging-0.1.0.dist-info/RECORD
