Metadata-Version: 2.1
Name: exa-logging
Version: 0.1.0
Summary: 
Author: Christopher Frige
Author-email: christopher.frige@exa.com.br
Requires-Python: >=3.7.3,<4.0.0
Classifier: Programming Language :: Python :: 3
Classifier: Programming Language :: Python :: 3.8
Classifier: Programming Language :: Python :: 3.9
Classifier: Programming Language :: Python :: 3.10
Classifier: Programming Language :: Python :: 3.11
Requires-Dist: json-log-formatter (>=0.5.2,<0.6.0)
